odoo/addons/hr_expense_advance_clearing/README.rst
odoo/addons/hr_expense_advance_clearing/__init__.py
odoo/addons/hr_expense_advance_clearing/__manifest__.py
odoo/addons/hr_expense_advance_clearing/data/advance_product.xml
odoo/addons/hr_expense_advance_clearing/i18n/hr_expense_advance_clearing.pot
odoo/addons/hr_expense_advance_clearing/i18n/it.po
odoo/addons/hr_expense_advance_clearing/i18n/th.po
odoo/addons/hr_expense_advance_clearing/i18n/th_TH.po
odoo/addons/hr_expense_advance_clearing/models/__init__.py
odoo/addons/hr_expense_advance_clearing/models/account_move.py
odoo/addons/hr_expense_advance_clearing/models/account_payment.py
odoo/addons/hr_expense_advance_clearing/models/hr_employee_base.py
odoo/addons/hr_expense_advance_clearing/models/hr_expense.py
odoo/addons/hr_expense_advance_clearing/models/hr_expense_sheet.py
odoo/addons/hr_expense_advance_clearing/readme/CONFIGURE.md
odoo/addons/hr_expense_advance_clearing/readme/CONTRIBUTORS.md
odoo/addons/hr_expense_advance_clearing/readme/DESCRIPTION.md
odoo/addons/hr_expense_advance_clearing/readme/USAGE.md
odoo/addons/hr_expense_advance_clearing/static/description/icon.png
odoo/addons/hr_expense_advance_clearing/static/description/index.html
odoo/addons/hr_expense_advance_clearing/tests/__init__.py
odoo/addons/hr_expense_advance_clearing/tests/test_hr_expense_advance_clearing.py
odoo/addons/hr_expense_advance_clearing/views/account_payment_view.xml
odoo/addons/hr_expense_advance_clearing/views/hr_employee_public_views.xml
odoo/addons/hr_expense_advance_clearing/views/hr_employee_views.xml
odoo/addons/hr_expense_advance_clearing/views/hr_expense_views.xml
odoo/addons/hr_expense_advance_clearing/wizard/__init__.py
odoo/addons/hr_expense_advance_clearing/wizard/account_payment_register.py
odoo_addon_hr_expense_advance_clearing-18.0.1.0.3.dist-info/METADATA
odoo_addon_hr_expense_advance_clearing-18.0.1.0.3.dist-info/WHEEL
odoo_addon_hr_expense_advance_clearing-18.0.1.0.3.dist-info/top_level.txt
odoo_addon_hr_expense_advance_clearing-18.0.1.0.3.dist-info/RECORD
