Metadata-Version: 2.1
Name: odoo-addon-hr_expense_advance_clearing
Version: 18.0.1.0.3
Requires-Python: >=3.10
Requires-Dist: odoo==18.0.*
Summary: Employee Advance and Clearing
Home-page: https://github.com/OCA/hr-expense
License: AGPL-3
Author: Ecosoft, Odoo Community Association (OCA)
Author-email: support@odoo-community.org
Classifier: Programming Language :: Python
Classifier: Framework :: Odoo
Classifier: Framework :: Odoo :: 18.0
Classifier: License :: OSI Approved :: GNU Affero General Public License v3
